django_logic/__init__.py
django_logic/commands.py
django_logic/constants.py
django_logic/exceptions.py
django_logic/logger.py
django_logic/process.py
django_logic/state.py
django_logic/transition.py
django_logic-0.1.6.dist-info/licenses/LICENSE
django_logic-0.1.6.dist-info/METADATA
django_logic-0.1.6.dist-info/WHEEL
django_logic-0.1.6.dist-info/top_level.txt
django_logic-0.1.6.dist-info/RECORD
